pycnnum/__init__.py
pycnnum/__version__.py
pycnnum/constants.py
pycnnum/pycnnum.py
pycnnum-2.1.1.dist-info/licenses/LICENSE
pycnnum-2.1.1.dist-info/WHEEL
pycnnum-2.1.1.dist-info/METADATA
pycnnum-2.1.1.dist-info/RECORD
