Metadata-Version: 2.4
Name: pycnnum
Version: 2.1.1
Summary: Chinese number <=> int/float conversion for Python3.8+
Author-email: Shuo Li <alwayszcold@gmail.com>
Requires-Python: >=3.8
Classifier: Intended Audience :: Developers
Classifier: License :: OSI Approved :: MIT License
Classifier: Programming Language :: Python :: 3
Classifier: Topic :: Software Development :: Libraries :: Python Modules
License-File: LICENSE
Requires-Dist: pytest ; extra == "dev"
Requires-Dist: pytest-cov ; extra == "dev"
Requires-Dist: mypy ; extra == "dev"
Requires-Dist: pylint ; extra == "dev"
Requires-Dist: black ; extra == "dev"
Requires-Dist: isort ; extra == "dev"
Requires-Dist: pdoc ; extra == "dev"
Requires-Dist: flit ; extra == "dev"
Requires-Dist: pdoc ; extra == "doc"
Requires-Dist: pytest ; extra == "test"
Requires-Dist: pytest-cov ; extra == "test"
Project-URL: Source, https://github.com/zcold/pycnnum
Provides-Extra: dev
Provides-Extra: doc
Provides-Extra: test
